MANIFEST.in
setup.py
jaci/__init__.py
jaci/cli.py
jaci/conf.py
jaci/core.py
jaci/models.py
jaci/mq.py
jaci/routes.py
jaci/server.py
jaci/util.py
jaci/version.py
jaci/wsgi.py
jaci.egg-info/PKG-INFO
jaci.egg-info/SOURCES.txt
jaci.egg-info/dependency_links.txt
jaci.egg-info/entry_points.txt
jaci.egg-info/not-zip-safe
jaci.egg-info/requires.txt
jaci.egg-info/top_level.txt
jaci/api/__init__.py
jaci/api/core.py
jaci/api/v1.py
jaci/static/404.html
jaci/static/500.html
jaci/static/css/ansi.css
jaci/static/css/buildbottv.css
jaci/static/css/fullscreen.css
jaci/static/css/jaci-icon-96.png
jaci/static/css/jaci-icon.png
jaci/static/css/jaci.css
jaci/static/css/paper.css
jaci/static/css/tango.css
jaci/static/js/app.0.common.js
jaci/static/js/app.0.models.js
jaci/static/js/app.1.auth.js
jaci/static/js/app.10.userprofile.js
jaci/static/js/app.2.index.js
jaci/static/js/app.3.newbuilder.js
jaci/static/js/app.4.build.js
jaci/static/js/app.5.preferences.js
jaci/static/js/app.6.fullscreen.js
jaci/static/js/app.7.splash.js
jaci/static/js/app.8.show.builder.js
jaci/static/js/app.9.editbuilder.js
jaci/static/js/app.js
jaci/static/js/templates/build-detail.html
jaci/static/js/templates/edit-builder.html
jaci/static/js/templates/fullscreen.html
jaci/static/js/templates/index.html
jaci/static/js/templates/login.html
jaci/static/js/templates/navbar.html
jaci/static/js/templates/new-builder.html
jaci/static/js/templates/preferences.html
jaci/static/js/templates/profile.html
jaci/static/js/templates/show-builder.html
jaci/static/js/templates/splash.html
jaci/static/vendor/angular/.bower.json
jaci/static/vendor/angular/README.md
jaci/static/vendor/angular/angular-csp.css
jaci/static/vendor/angular/angular.js
jaci/static/vendor/angular/angular.min.js
jaci/static/vendor/angular/angular.min.js.gzip
jaci/static/vendor/angular/angular.min.js.map
jaci/static/vendor/angular/bower.json
jaci/static/vendor/angular/index.js
jaci/static/vendor/angular/package.json
jaci/static/vendor/angular-cookies/.bower.json
jaci/static/vendor/angular-cookies/README.md
jaci/static/vendor/angular-cookies/angular-cookies.js
jaci/static/vendor/angular-cookies/angular-cookies.min.js
