Metadata-Version: 1.0
Name: jaci
Version: 0.0.31
Summary: continuous integration for the people
Home-page: http://falcao.it/jaci
Author: Gabriel Falcao
Author-email: gabriel@nacaolivre.org
License: UNKNOWN
Platform: UNKNOWN
